pyreadable/__init__.py
pyreadable/main.py
pyreadable/readablity.py
pyreadable-0.1.3.dist-info/METADATA
pyreadable-0.1.3.dist-info/WHEEL
pyreadable-0.1.3.dist-info/top_level.txt
pyreadable-0.1.3.dist-info/RECORD
