Metadata-Version: 2.1
Name: pyreadable
Version: 0.1.3
Summary: Check PDFs for Machine Readability
Author: Archit Anant
Classifier: Intended Audience :: Developers
Classifier: Programming Language :: Python :: 3
Classifier: Operating System :: OS Independent
Classifier: Topic :: Text Processing :: General
Classifier: Topic :: Utilities
Requires-Python: >=3.7
Requires-Dist: pymupdf >=1.25.5
Requires-Dist: PyPDF2 >=3.0.1
